data_mem.v
// data_mem.v
module data_mem (
    input  clk,
    input  MemRead,
    input  MemWrite,
    input  [31:0] addr,
    input  [31:0] write_data,
    output reg [31:0] read_data
);
    reg [31:0] mem [0:63]; // 64 words (256 bytes)

    integer i;
    initial begin
        for (i=0; i<64; i=i+1) mem[i] = 0;
        // Test ke liye: maan lo mem[1] = 32'h0000000A; etc. agar chaho
    end

    wire [5:0] word_addr = addr[7:2];  // word aligned

    // READ: combinational
    always @(*) begin
        if (MemRead)
            read_data = mem[word_addr];
        else
            read_data = 32'd0;
    end

    // WRITE: synchronous
    always @(posedge clk) begin
        if (MemWrite)
            mem[word_addr] <= write_data;
    end
endmodule

alu.v
module alu (
    input  [31:0] a, b,
    input  [3:0] alu_op,
    output reg [31:0] result
);
    always @(*) begin
        case (alu_op)
            4'b0000: result = a + b;      // ADD
            4'b0001: result = a - b;      // SUB (for BEQ)
            default: result = a + b;
        endcase
    end
endmodule

alu_control.v
module alu_control (
    input  [6:0] opcode,
    input  [2:0] funct3,
    input  [6:0] funct7,
    output reg [3:0] alu_op
);
    always @(*) begin
        case (opcode)
            7'b0110011: alu_op = 4'b0000;  // ADD (default)
            7'b0010011: alu_op = 4'b0000;  // ADDI
            7'b0000011: alu_op = 4'b0000;  // LW
            7'b0100011: alu_op = 4'b0000;  // SW
            7'b1100011: alu_op = 4'b0001;  // BEQ → SUB!
            default:    alu_op = 4'b0000;
        endcase
    end
endmodule

imm_gen.v
module imm_gen (
    input [31:0] instr,
    input [6:0] opcode,
    output reg [31:0] imm
);
    always @(*) begin
        case(opcode)
            // I-type: ADDI, LW
            7'b0010011: imm = {{20{instr[31]}}, instr[31:20]};
            7'b0000011: imm = {{20{instr[31]}}, instr[31:20]};
            
            // S-type: SW
            7'b0100011: imm = {{20{instr[31]}}, instr[31:25], instr[11:7]};
            
            // B-type: BEQ (CRITICAL!)
            7'b1100011: imm = {{19{instr[31]}}, instr[31], instr[7], 
                               instr[30:25], instr[11:8], 1'b0};
            
            default: imm = 32'h0;
        endcase
    end
endmodule

regfile.v
module regfile (
    input clk,
    input [4:0] rs1, rs2, rd,
    input [31:0] write_data,
    input reg_write,
    output [31:0] read_data1, read_data2
);
    reg [31:0] registers [31:0];
    
    integer i;
    initial for(i=0; i<32; i=i+1) registers[i] = 0;
    
    // x0 ALWAYS 0 (even if write attempt)
    assign read_data1 = (rs1 == 5'd0) ? 32'd0 : registers[rs1];
    assign read_data2 = (rs2 == 5'd0) ? 32'd0 : registers[rs2];
    
    always @(posedge clk)
        if (reg_write && rd != 5'd0)
            registers[rd] <= write_data;
endmodule

control.v
// control.v
module control (
    input  [6:0] opcode,
    output reg   RegWrite,
    output reg   ALUSrc,
    output reg   MemRead,
    output reg   MemWrite,
    output reg   MemToReg,
    output reg   Branch
);
    always @(*) begin
        // Default sab 0
        RegWrite = 0;
        ALUSrc   = 0;
        MemRead  = 0;
        MemWrite = 0;
        MemToReg = 0;
        Branch   = 0;

        case (opcode)
            7'b0110011: begin // R-type: ADD,SUB,AND,OR,SLT
                RegWrite = 1;
                ALUSrc   = 0;
            end

            7'b0010011: begin // I-type: ADDI
                RegWrite = 1;
                ALUSrc   = 1;
            end

            7'b0000011: begin // LW
                RegWrite = 1;
                ALUSrc   = 1;
                MemRead  = 1;
                MemToReg = 1;
            end

            7'b0100011: begin // SW
                RegWrite = 0;
                ALUSrc   = 1;
                MemWrite = 1;
            end

            7'b1100011: begin // BEQ
                RegWrite = 0;
                ALUSrc   = 0;
                Branch   = 1;
            end

            default: begin
                // NOP / unknown → sab 0 hi rahne do
            end
        endcase
    end
endmodule

decoder.v
module decoder (
    input [31:0] instr,
    output [6:0] opcode,
    output [4:0] rs1, rs2, rd,
    output [2:0] funct3,
    output [6:0] funct7
);
    assign opcode = instr[6:0];
    assign rd     = instr[11:7];
    assign funct3 = instr[14:12];
    assign rs1    = instr[19:15];
    assign rs2    = instr[24:20];
    assign funct7 = instr[31:25];
endmodule

instr_mem.v
// instr_mem.v (UPDATED - correct BEQ encoding)
module instr_mem(input [31:0] addr, output reg [31:0] instr);
    reg [31:0] rom[0:15];
    
    initial begin
        rom[0] = 32'h00500093;  // ADDI x1,x0,5
        rom[1] = 32'h00500113;  // ADDI x2,x0,5
        rom[2] = 32'h00208463;  // BEQ x1,x2,+8  (CORRECTED!)
        rom[3] = 32'h00100193;  // ADDI x3,x0,1 (skip if branch)
        rom[4] = 32'h00900193;  // ADDI x3,x0,9 (branch target)
        rom[5] = 32'h00000000;  // NOP
    end
    
    always @(*) instr = rom[addr[31:2]];
endmodule

pc_module.v
module pc_module (
    input clk, rst, 
    input [31:0] pc_next,
    output reg [31:0] pc
);
    always @(posedge clk or posedge rst) begin
        if (rst)
            pc <= 32'h0000_0000;
        else
            pc <= pc_next;
    end
endmodule

riscv_top.v
module riscv_top (
    input clk, rst,
    output [31:0] pc_out, pc_next,
    output [31:0] instr_out, alu_out,
    output [31:0] reg1_out, reg2_out, imm_out,
    output [6:0] opcode_out,
    output [4:0] rs1_out, rs2_out, rd_out,
    output RegWrite, ALUSrc, MemRead, MemWrite, MemToReg, Branch,
    output Zero,
    output [31:0] read_data_mem
);
    // Internal wires
    wire [31:0] pc, instr, reg1, reg2, imm, alu_result;
    wire [31:0] alu_b, writeback_data;
    wire [6:0] opcode;
    wire [4:0] rs1, rs2, rd;
    wire [2:0] funct3;
    wire [6:0] funct7;
    wire reg_write, alusrc, mem_read, mem_write, memtoreg, branch;
    wire zero_flag;
    wire take_branch;
    wire [31:0] pc_plus4, pc_branch;
    wire [31:0] data_mem_read;
    
    // ==== FETCH ====
    pc_module PC(.clk(clk), .rst(rst), .pc_next(pc_next), .pc(pc));
    instr_mem IMEM(.addr(pc), .instr(instr));
    
    // ==== DECODE ====
    decoder DEC(.instr(instr), .opcode(opcode), .rs1(rs1), .rs2(rs2), .rd(rd),
                .funct3(funct3), .funct7(funct7));
    
    // ==== CONTROL (NEW!) ====
    control CTRL(.opcode(opcode),
                 .RegWrite(reg_write), .ALUSrc(alusrc),
                 .MemRead(mem_read), .MemWrite(mem_write),
                 .MemToReg(memtoreg), .Branch(branch));
    
    // ==== REGISTERS ====
    regfile RF(.clk(clk), .rs1(rs1), .rs2(rs2), .rd(rd),
               .write_data(writeback_data), .reg_write(reg_write),
               .read_data1(reg1), .read_data2(reg2));
    
    // ==== IMMEDIATE ====
    imm_gen IMMG(.instr(instr), .opcode(opcode), .imm(imm));
    
    // ==== ALU ====
    // Correct: BEQ ke liye ALUSrc=0
    assign alu_b = (branch && (opcode == 7'b1100011)) ? reg2 : (alusrc ? imm : reg2);

    wire [3:0] alu_op;
    alu_control ALU_CTRL(.opcode(opcode), .funct3(funct3), .funct7(funct7), .alu_op(alu_op));
    alu ALU_INST(.a(reg1), .b(alu_b), .alu_op(alu_op), .result(alu_result));
    assign zero_flag = (alu_result == 32'd0);

    // Make sure ye lines hain:
    assign pc_plus4 = pc + 32'd4;
    assign pc_branch = pc + imm;      // ← Ye imm use kar raha?
    assign take_branch = branch & zero_flag;
    assign pc_next = take_branch ? pc_branch : pc_plus4;

    
    // ==== DATA MEMORY (NEW!) ====
    data_mem DMEM(.clk(clk),
                  .MemRead(mem_read), .MemWrite(mem_write),
                  .addr(alu_result), .write_data(reg2),
                  .read_data(data_mem_read));
    
    // ==== WRITEBACK ====
    assign writeback_data = memtoreg ? data_mem_read : alu_result;
    
    // ==== BRANCH LOGIC (NEW!) ====
    assign take_branch = branch & zero_flag;  // BEQ: if Zero & Branch
    assign pc_plus4 = pc + 32'd4;
    assign pc_branch = pc + imm;
    assign pc_next = take_branch ? pc_branch : pc_plus4;
    
    // ==== DEBUG OUTPUTS ====
    assign pc_out = pc;
    assign instr_out = instr;
    assign alu_out = alu_result;
    assign reg1_out = reg1;
    assign reg2_out = reg2;
    assign imm_out = imm;
    assign opcode_out = opcode;
    assign rs1_out = rs1;
    assign rs2_out = rs2;
    assign rd_out = rd;
    assign RegWrite = reg_write;
    assign ALUSrc = alusrc;
    assign MemRead = mem_read;
    assign MemWrite = mem_write;
    assign MemToReg = memtoreg;
    assign Branch = branch;
    assign Zero = zero_flag;
    assign read_data_mem = data_mem_read;
endmodule

tb_riscv.v
`timescale 1ns/1ps

module tb_riscv;
    reg clk=0, rst=1;
    
    // Outputs from top
    wire [31:0] pc_out, pc_next;
    wire [31:0] instr_out, alu_out;
    wire [31:0] reg1_out, reg2_out, imm_out;
    wire [6:0] opcode_out;
    wire [4:0] rs1_out, rs2_out, rd_out;
    wire RegWrite, ALUSrc, MemRead, MemWrite, MemToReg, Branch;
    wire Zero;
    wire [31:0] read_data_mem;
    
    // Instantiate top
    riscv_top DUT(
        .clk(clk), .rst(rst),
        .pc_out(pc_out), .pc_next(pc_next),
        .instr_out(instr_out), .alu_out(alu_out),
        .reg1_out(reg1_out), .reg2_out(reg2_out), .imm_out(imm_out),
        .opcode_out(opcode_out),
        .rs1_out(rs1_out), .rs2_out(rs2_out), .rd_out(rd_out),
        .RegWrite(RegWrite), .ALUSrc(ALUSrc),
        .MemRead(MemRead), .MemWrite(MemWrite),
        .MemToReg(MemToReg), .Branch(Branch),
        .Zero(Zero),
        .read_data_mem(read_data_mem)
    );
    
    // Clock generation
    always #5 clk = ~clk;
    
    // VCD dump
    initial begin
        $dumpfile("riscv_day3.vcd");
        $dumpvars(0, tb_riscv);
    end
    
    // Test sequence
    initial begin
        $display("╔════════════════════════════════════════╗");
        $display("║ DAY 3: CONTROL + BRANCH TEST ║");
        $display("║ Expect: x1=5, x2=5, x3=9 (NOT 1)  ║");
        $display("╚════════════════════════════════════════╝");
        
        #20 rst = 0;  // Release reset
        
        // Run 30 cycles
        repeat(30) @(posedge clk);
        
        $display("\n╔════════════════════════════════════════╗");
        $display("║ TEST COMPLETE - Check GTKWave ║");
        $display("╚════════════════════════════════════════╝");
        $finish;
    end
    
    // MONITOR: Print every cycle
    always @(posedge clk) begin
        if (!rst) begin
            $display("t=%0t | PC=0x%02h | opcode=%2d | instr=0x%h | ALU=0x%h | Zero=%b | Branch=%b | RegWr=%b",
                     $time, pc_out[7:0], opcode_out, instr_out, alu_out, Zero, Branch, RegWrite);
        end
    end
    
    // SPECIAL: Print x1, x2, x3 register values
    always @(posedge clk) begin
        if (!rst && pc_out >= 32'h8) begin  // After BEQ
            $display("  → x1=%d, x2=%d, x3=%d, RegWrite=%b, rd=%d",
                     DUT.RF.registers[1], DUT.RF.registers[2], DUT.RF.registers[3],
                     RegWrite, rd_out);
        end
    end

    always @(posedge clk) begin
        if (!rst && Branch)
            $display("BEQ: pc=0x%h imm=0x%h pc_branch=0x%h",
                    pc_out, imm_out, pc_out + imm_out);
    end

endmodule

riscv_day3.vcd
$date
	Tue Jan 06 23:23:03 2026
$end
$version
	Icarus Verilog
$end
$timescale
	1ps
$end
$scope module tb_riscv $end
$var wire 32 ! pc_next [31:0] $end
$var wire 5 " rs2_out [4:0] $end
$var wire 5 # rs1_out [4:0] $end
$var wire 32 $ reg2_out [31:0] $end
$var wire 32 % reg1_out [31:0] $end
$var wire 32 & read_data_mem [31:0] $end
$var wire 5 ' rd_out [4:0] $end
$var wire 32 ( pc_out [31:0] $end
$var wire 7 ) opcode_out [6:0] $end
$var wire 32 * instr_out [31:0] $end
$var wire 32 + imm_out [31:0] $end
$var wire 32 , alu_out [31:0] $end
$var wire 1 - Zero $end
$var wire 1 . RegWrite $end
$var wire 1 / MemWrite $end
$var wire 1 0 MemToReg $end
$var wire 1 1 MemRead $end
$var wire 1 2 Branch $end
$var wire 1 3 ALUSrc $end
$var reg 1 4 clk $end
$var reg 1 5 rst $end
$scope module DUT $end
$var wire 1 3 ALUSrc $end
$var wire 1 2 Branch $end
$var wire 1 1 MemRead $end
$var wire 1 0 MemToReg $end
$var wire 1 / MemWrite $end
$var wire 1 . RegWrite $end
$var wire 1 - Zero $end
$var wire 32 6 alu_out [31:0] $end
$var wire 1 4 clk $end
$var wire 32 7 imm_out [31:0] $end
$var wire 32 8 instr_out [31:0] $end
$var wire 7 9 opcode_out [6:0] $end
$var wire 32 : pc_branch [31:0] $end
$var wire 32 ; pc_next [31:0] $end
$var wire 32 < pc_out [31:0] $end
$var wire 32 = pc_plus4 [31:0] $end
$var wire 5 > rd_out [4:0] $end
$var wire 32 ? read_data_mem [31:0] $end
$var wire 32 @ reg1_out [31:0] $end
$var wire 32 A reg2_out [31:0] $end
$var wire 5 B rs1_out [4:0] $end
$var wire 5 C rs2_out [4:0] $end
$var wire 1 5 rst $end
$var wire 1 D take_branch $end
$var wire 1 E zero_flag $end
$var wire 32 F writeback_data [31:0] $end
$var wire 5 G rs2 [4:0] $end
$var wire 5 H rs1 [4:0] $end
$var wire 1 I reg_write $end
$var wire 32 J reg2 [31:0] $end
$var wire 32 K reg1 [31:0] $end
$var wire 5 L rd [4:0] $end
$var wire 32 M pc [31:0] $end
$var wire 7 N opcode [6:0] $end
$var wire 1 O memtoreg $end
$var wire 1 P mem_write $end
$var wire 1 Q mem_read $end
$var wire 32 R instr [31:0] $end
$var wire 32 S imm [31:0] $end
$var wire 7 T funct7 [6:0] $end
$var wire 3 U funct3 [2:0] $end
$var wire 32 V data_mem_read [31:0] $end
$var wire 1 W branch $end
$var wire 1 X alusrc $end
$var wire 32 Y alu_result [31:0] $end
$var wire 4 Z alu_op [3:0] $end
$var wire 32 [ alu_b [31:0] $end
$scope module ALU_CTRL $end
$var wire 7 \ opcode [6:0] $end
$var wire 7 ] funct7 [6:0] $end
$var wire 3 ^ funct3 [2:0] $end
$var reg 4 _ alu_op [3:0] $end
$upscope $end
$scope module ALU_INST $end
$var wire 4 ` alu_op [3:0] $end
$var wire 32 a b [31:0] $end
$var wire 32 b a [31:0] $end
$var reg 32 c result [31:0] $end
$upscope $end
$scope module CTRL $end
$var wire 7 d opcode [6:0] $end
$var reg 1 X ALUSrc $end
$var reg 1 W Branch $end
$var reg 1 Q MemRead $end
$var reg 1 O MemToReg $end
$var reg 1 P MemWrite $end
$var reg 1 I RegWrite $end
$upscope $end
$scope module DEC $end
$var wire 5 e rs2 [4:0] $end
$var wire 5 f rs1 [4:0] $end
$var wire 5 g rd [4:0] $end
$var wire 7 h opcode [6:0] $end
$var wire 32 i instr [31:0] $end
$var wire 7 j funct7 [6:0] $end
$var wire 3 k funct3 [2:0] $end
$upscope $end
$scope module DMEM $end
$var wire 1 Q MemRead $end
$var wire 1 P MemWrite $end
$var wire 32 l addr [31:0] $end
$var wire 1 4 clk $end
$var wire 32 m write_data [31:0] $end
$var wire 6 n word_addr [5:0] $end
$var reg 32 o read_data [31:0] $end
$var integer 32 p i [31:0] $end
$upscope $end
$scope module IMEM $end
$var wire 32 q addr [31:0] $end
$var reg 32 r instr [31:0] $end
$upscope $end
$scope module IMMG $end
$var wire 32 s instr [31:0] $end
$var wire 7 t opcode [6:0] $end
$var reg 32 u imm [31:0] $end
$upscope $end
$scope module PC $end
$var wire 1 4 clk $end
$var wire 32 v pc_next [31:0] $end
$var wire 1 5 rst $end
$var reg 32 w pc [31:0] $end
$upscope $end
$scope module RF $end
$var wire 1 4 clk $end
$var wire 5 x rd [4:0] $end
$var wire 1 I reg_write $end
$var wire 5 y rs1 [4:0] $end
$var wire 5 z rs2 [4:0] $end
$var wire 32 { write_data [31:0] $end
$var wire 32 | read_data2 [31:0] $end
$var wire 32 } read_data1 [31:0] $end
$var integer 32 ~ i [31:0] $end
$upscope $end
$upscope $end
$upscope $end
$enddefinitions $end
$comment Show the parameter values. $end
$dumpall
$end
#0
$dumpvars
b100000 ~
b0 }
b0 |
b101 {
b101 z
b0 y
b1 x
b0 w
b100 v
b101 u
b10011 t
b10100000000000010010011 s
b10100000000000010010011 r
b0 q
b1000000 p
b0 o
b1 n
b0 m
b101 l
b0 k
b0 j
b10100000000000010010011 i
b10011 h
b1 g
b0 f
b101 e
b10011 d
b101 c
b0 b
b101 a
b0 `
b0 _
b0 ^
b0 ]
b10011 \
b101 [
b0 Z
b101 Y
1X
0W
b0 V
b0 U
b0 T
b101 S
b10100000000000010010011 R
0Q
0P
0O
b10011 N
b0 M
b1 L
b0 K
b0 J
1I
b0 H
b101 G
b101 F
0E
0D
b101 C
b0 B
b0 A
b0 @
b0 ?
b1 >
b100 =
b0 <
b100 ;
b101 :
b10011 9
b10100000000000010010011 8
b101 7
b101 6
15
04
13
02
01
00
0/
1.
0-
b101 ,
b101 +
b10100000000000010010011 *
b10011 )
b0 (
b1 '
b0 &
b0 %
b0 $
b0 #
b101 "
b100 !
$end
#5000
14
#10000
04
#15000
14
#20000
04
05
#25000
b10 '
b10 >
b10 L
b10 g
b10 x
b1000 !
b1000 ;
b1000 v
b10100000000000100010011 *
b10100000000000100010011 8
b10100000000000100010011 R
b10100000000000100010011 i
b10100000000000100010011 r
b10100000000000100010011 s
b1001 :
b1000 =
b100 (
b100 <
b100 M
b100 q
b100 w
14
#30000
04
#35000
b0 n
b0 F
b0 {
1D
1-
1E
b0 ,
b0 6
b0 Y
b0 c
b0 l
b101 $
b101 A
b101 J
b101 m
b101 |
b101 %
b101 @
b101 K
b101 b
b101 }
12
1W
03
0X
0.
0I
b1 Z
b1 _
b1 `
b10 "
b10 C
b10 G
b10 e
b10 z
b1 #
b1 B
b1 H
b1 f
b1 y
b1000 '
b1000 >
b1000 L
b1000 g
b1000 x
b1100011 )
b1100011 9
b1100011 N
b1100011 \
b1100011 d
b1100011 h
b1100011 t
b1000 +
b1000 7
b1000 S
b1000 u
b10000 !
b10000 ;
b10000 v
b1000001000010001100011 *
b1000001000010001100011 8
b1000001000010001100011 R
b1000001000010001100011 i
b1000001000010001100011 r
b1000001000010001100011 s
b10000 :
b1100 =
b1000 (
b1000 <
b1000 M
b1000 q
b1000 w
14
#40000
04
#45000
b10 n
b1001 F
b1001 {
b1001 [
b1001 a
0-
0E
b1001 ,
b1001 6
b1001 Y
b1001 c
b1001 l
0D
b0 $
b0 A
b0 J
b0 m
b0 |
b0 %
b0 @
b0 K
b0 b
b0 }
b0 Z
b0 _
b0 `
13
1X
1.
1I
02
0W
b1001 "
b1001 C
b1001 G
b1001 e
b1001 z
b0 #
b0 B
b0 H
b0 f
b0 y
b11 '
b11 >
b11 L
b11 g
b11 x
b10011 )
b10011 9
b10011 N
b10011 \
b10011 d
b10011 h
b10011 t
b1001 +
b1001 7
b1001 S
b1001 u
b10100 !
b10100 ;
b10100 v
b100100000000000110010011 *
b100100000000000110010011 8
b100100000000000110010011 R
b100100000000000110010011 i
b100100000000000110010011 r
b100100000000000110010011 s
b11001 :
b10100 =
b10000 (
b10000 <
b10000 M
b10000 q
b10000 w
14
#50000
04
#55000
b0 n
b0 F
b0 {
1-
1E
b0 ,
b0 6
b0 Y
b0 c
b0 l
b0 [
b0 a
03
0X
0.
0I
b0 "
b0 C
b0 G
b0 e
b0 z
b0 '
b0 >
b0 L
b0 g
b0 x
b0 )
b0 9
b0 N
b0 \
b0 d
b0 h
b0 t
b0 +
b0 7
b0 S
b0 u
b11000 !
b11000 ;
b11000 v
b0 *
b0 8
b0 R
b0 i
b0 r
b0 s
b10100 :
b11000 =
b10100 (
b10100 <
b10100 M
b10100 q
b10100 w
14
#60000
04
#65000
bx [
bx a
bx n
bx F
bx {
x-
xE
bx ,
bx 6
bx Y
bx c
bx l
bx $
bx A
bx J
bx m
bx |
bx %
bx @
bx K
bx b
bx }
bx T
bx ]
bx j
bx "
bx C
bx G
bx e
bx z
bx #
bx B
bx H
bx f
bx y
bx U
bx ^
bx k
bx '
bx >
bx L
bx g
bx x
bx )
bx 9
bx N
bx \
bx d
bx h
bx t
b11100 !
b11100 ;
b11100 v
bx *
bx 8
bx R
bx i
bx r
bx s
b11000 :
b11100 =
b11000 (
b11000 <
b11000 M
b11000 q
b11000 w
14
#70000
04
#75000
b100000 !
b100000 ;
b100000 v
b11100 :
b100000 =
b11100 (
b11100 <
b11100 M
b11100 q
b11100 w
14
#80000
04
#85000
b100100 !
b100100 ;
b100100 v
b100000 :
b100100 =
b100000 (
b100000 <
b100000 M
b100000 q
b100000 w
14
#90000
04
#95000
b101000 !
b101000 ;
b101000 v
b100100 :
b101000 =
b100100 (
b100100 <
b100100 M
b100100 q
b100100 w
14
#100000
04
#105000
b101100 !
b101100 ;
b101100 v
b101000 :
b101100 =
b101000 (
b101000 <
b101000 M
b101000 q
b101000 w
14
#110000
04
#115000
b110000 !
b110000 ;
b110000 v
b101100 :
b110000 =
b101100 (
b101100 <
b101100 M
b101100 q
b101100 w
14
#120000
04
#125000
b110100 !
b110100 ;
b110100 v
b110000 :
b110100 =
b110000 (
b110000 <
b110000 M
b110000 q
b110000 w
14
#130000
04
#135000
b111000 !
b111000 ;
b111000 v
b110100 :
b111000 =
b110100 (
b110100 <
b110100 M
b110100 q
b110100 w
14
#140000
04
#145000
b111100 !
b111100 ;
b111100 v
b111000 :
b111100 =
b111000 (
b111000 <
b111000 M
b111000 q
b111000 w
14
#150000
04
#155000
b1000000 !
b1000000 ;
b1000000 v
b111100 :
b1000000 =
b111100 (
b111100 <
b111100 M
b111100 q
b111100 w
14
#160000
04
#165000
b1000100 !
b1000100 ;
b1000100 v
b1000000 :
b1000100 =
b1000000 (
b1000000 <
b1000000 M
b1000000 q
b1000000 w
14
#170000
04
#175000
b1001000 !
b1001000 ;
b1001000 v
b1000100 :
b1001000 =
b1000100 (
b1000100 <
b1000100 M
b1000100 q
b1000100 w
14
#180000
04
#185000
b1001100 !
b1001100 ;
b1001100 v
b1001000 :
b1001100 =
b1001000 (
b1001000 <
b1001000 M
b1001000 q
b1001000 w
14
#190000
04
#195000
b1010000 !
b1010000 ;
b1010000 v
b1001100 :
b1010000 =
b1001100 (
b1001100 <
b1001100 M
b1001100 q
b1001100 w
14
#200000
04
#205000
b1010100 !
b1010100 ;
b1010100 v
b1010000 :
b1010100 =
b1010000 (
b1010000 <
b1010000 M
b1010000 q
b1010000 w
14
#210000
04
#215000
b1011000 !
b1011000 ;
b1011000 v
b1010100 :
b1011000 =
b1010100 (
b1010100 <
b1010100 M
b1010100 q
b1010100 w
14
#220000
04
#225000
b1011100 !
b1011100 ;
b1011100 v
b1011000 :
b1011100 =
b1011000 (
b1011000 <
b1011000 M
b1011000 q
b1011000 w
14
#230000
04
#235000
b1100000 !
b1100000 ;
b1100000 v
b1011100 :
b1100000 =
b1011100 (
b1011100 <
b1011100 M
b1011100 q
b1011100 w
14
#240000
04
#245000
b1100100 !
b1100100 ;
b1100100 v
b1100000 :
b1100100 =
b1100000 (
b1100000 <
b1100000 M
b1100000 q
b1100000 w
14
#250000
04
#255000
b1101000 !
b1101000 ;
b1101000 v
b1100100 :
b1101000 =
b1100100 (
b1100100 <
b1100100 M
b1100100 q
b1100100 w
14
#260000
04
#265000
b1101100 !
b1101100 ;
b1101100 v
b1101000 :
b1101100 =
b1101000 (
b1101000 <
b1101000 M
b1101000 q
b1101000 w
14
#270000
04
#275000
b1110000 !
b1110000 ;
b1110000 v
b1101100 :
b1110000 =
b1101100 (
b1101100 <
b1101100 M
b1101100 q
b1101100 w
14
#280000
04
#285000
b1110100 !
b1110100 ;
b1110100 v
b1110000 :
b1110100 =
b1110000 (
b1110000 <
b1110000 M
b1110000 q
b1110000 w
14
#290000
04
#295000
b1111000 !
b1111000 ;
b1111000 v
b1110100 :
b1111000 =
b1110100 (
b1110100 <
b1110100 M
b1110100 q
b1110100 w
14
#300000
04
#305000
b1111100 !
b1111100 ;
b1111100 v
b1111000 :
b1111100 =
b1111000 (
b1111000 <
b1111000 M
b1111000 q
b1111000 w
14
#310000
04
#315000
b10000000 !
b10000000 ;
b10000000 v
b1111100 :
b10000000 =
b1111100 (
b1111100 <
b1111100 M
b1111100 q
b1111100 w
14
